a_pandas_ex_df_updater/LICENSE
a_pandas_ex_df_updater/README.MD
a_pandas_ex_df_updater/__init__.py
a_pandas_ex_df_updater/requirements.txt
a_pandas_ex_df_updater/thirdparty.json
a_pandas_ex_df_updater-0.11.dist-info/LICENSE.rst
a_pandas_ex_df_updater-0.11.dist-info/METADATA
a_pandas_ex_df_updater-0.11.dist-info/WHEEL
a_pandas_ex_df_updater-0.11.dist-info/top_level.txt
a_pandas_ex_df_updater-0.11.dist-info/RECORD
